{
  "type": "Route-Stop",
  "version": "1.0",
  "generated_timestamp": "2024-11-16T19:57:57.725+08:00",
  "data": {
    "route_stops": [
      {
        "stop_seq": 1,
        "stop_id": 20012959,
        "name_tc": "第一街, 近正街街市",
        "name_sc": "第一街, 近正街街市 ",
        "name_en": "First Street, near Centre Street Market"
      },
      {
        "stop_seq": 2,
        "stop_id": 20003567,
        "name_tc": "列堤頓道, 近巴丙頓道",
        "name_sc": "列堤顿道, 近巴丙顿道",
        "name_en": "Lyttelton Road, near Babington Path"
      },
      {
        "stop_seq": 3,
        "stop_id": 20000302,
        "name_tc": "羅便臣道, 秀麗閣對面",
        "name_sc": "罗便臣道, 秀丽阁对面",
        "name_en": "Robinson Road, opposite Serene Court"
      },
      {
        "stop_seq": 4,
        "stop_id": 20012960,
        "name_tc": "干德道, 年豐園對面",
        "name_sc": "干德道, 年丰园对面",
        "name_en": "Conduit Road, opposite to Skyline Mansion"
      },
      {
        "stop_seq": 5,
        "stop_id": 20012961,
        "name_tc": "干德道, 近帝豪閣",
        "name_sc": "干德道, 近帝豪阁 ",
        "name_en": "Conduit Road, near Imperial Court"
      },
      {
        "stop_seq": 6,
        "stop_id": 20012962,
        "name_tc": "干德道, 近嘉富臺",
        "name_sc": "干德道, 近嘉富台 ",
        "name_en": "Conduit Road, near Prosperous Height"
      },
      {
        "stop_seq": 7,
        "stop_id": 20012963,
        "name_tc": "干德道, 近殷樺花園２期",
        "name_sc": "干德道, 近殷桦花园２期 ",
        "name_en": "Conduit Road, near Blessings Garden Phase 2"
      },
      {
        "stop_seq": 8,
        "stop_id": 20012964,
        "name_tc": "干德道, 近The Icon",
        "name_sc": "干德道, 近The Icon ",
        "name_en": "Conduit Road, near The Icon"
      },
      {
        "stop_seq": 9,
        "stop_id": 20012965,
        "name_tc": "干德道, 近慧豪閣",
        "name_sc": "干德道, 近慧豪阁 ",
        "name_en": "Conduit Road, near Elegant Garden Block B"
      },
      {
        "stop_seq": 10,
        "stop_id": 20012966,
        "name_tc": "干德道, 近麗豪閣",
        "name_sc": "干德道, 近丽豪阁 ",
        "name_en": "Conduit Road, near Tycoon Court"
      },
      {
        "stop_seq": 11,
        "stop_id": 20000325,
        "name_tc": "羅便臣道, 近利德大廈",
        "name_sc": "罗便臣道, 近利德大厦",
        "name_en": "Robinson Road, near Right Mansion"
      },
      {
        "stop_seq": 12,
        "stop_id": 20012967,
        "name_tc": "羅便臣道, 近宜新大廈",
        "name_sc": "罗便臣道, 近宜新大厦",
        "name_en": "Robinson Road, near East Sun Mansion"
      },
      {
        "stop_seq": 13,
        "stop_id": 20012970,
        "name_tc": "醫院道, 近中西區聖安多尼學校",
        "name_sc": "医院道, 近中西区圣安多尼学校",
        "name_en": "Hospital Road, near C & W District St.anthony's School"
      },
      {
        "stop_seq": 14,
        "stop_id": 20012969,
        "name_tc": "第一街, 近正街街市",
        "name_sc": "第一街, 近正街街市 ",
        "name_en": "First Street, near Centre Street Market"
      }
    ],
    "data_timestamp": "2024-10-31T18:50:31.564+08:00"
  }
}