{
  "type": "Route-Stop",
  "version": "1.0",
  "generated_timestamp": "2024-09-20T12:44:17.482+08:00",
  "data": {
    "route_stops": [
      {
        "stop_seq": 1,
        "stop_id": 20014659,
        "name_tc": "康盛花園巴士總站, 景嶺書院外",
        "name_sc": "康盛花园巴士总站, 景岭书院外",
        "name_en": "Hong Sing Garden Bus Terminus, outside King Ling College"
      },
      {
        "stop_seq": 2,
        "stop_id": 20002003,
        "name_tc": "寶琳北路, 康盛花園外",
        "name_sc": "宝琳北路, 康盛花园外",
        "name_en": "Po Lam Road North, outside Hong Sing Garden"
      },
      {
        "stop_seq": 3,
        "stop_id": 20002020,
        "name_tc": "寶琳北路, 景明苑旭景閣外",
        "name_sc": "宝琳北路, 景明苑旭景阁外",
        "name_en": "Po Lam Road North, outside Yuk King House, King Ming Court"
      },
      {
        "stop_seq": 4,
        "stop_id": 20001169,
        "name_tc": "寶琳北路, 寶仁樓對面",
        "name_sc": "宝琳北路, 宝仁楼对面",
        "name_en": "Po Lam Road North, opposite Po Yan House"
      },
      {
        "stop_seq": 5,
        "stop_id": 20002005,
        "name_tc": "寶琳北路, 樂善堂劉德小學對面",
        "name_sc": "宝琳北路, 乐善堂刘德小学对面",
        "name_en": "Po Lam Road North, opposite Lok Sin Tong Lau Tak Primary School"
      },
      {
        "stop_seq": 6,
        "stop_id": 20014861,
        "name_tc": "寶豐路, 新都城外",
        "name_sc": "宝丰路, 新都城外",
        "name_en": "Po Fung Road, outside Metro City"
      },
      {
        "stop_seq": 7,
        "stop_id": 20014660,
        "name_tc": "寶豐路, 順德聯誼總會梁潔華小學外",
        "name_sc": "宝丰路, 顺德联谊总会梁洁华小学外",
        "name_en": "Po Fung Road, outside STFA Leung Kit Wah Primary School"
      },
      {
        "stop_seq": 8,
        "stop_id": 20014661,
        "name_tc": "寶康路, 茵怡花園外",
        "name_sc": "宝康路, 茵怡花园外",
        "name_en": "Po Hong Road, outside Verbena Heights"
      },
      {
        "stop_seq": 9,
        "stop_id": 20014663,
        "name_tc": "寶康路, 寶康公園外",
        "name_sc": "宝康路, 宝康公园外",
        "name_en": "Po Hong Road, outside Po Hong Park"
      },
      {
        "stop_seq": 10,
        "stop_id": 20002010,
        "name_tc": "太子道東, 采頤花園對面",
        "name_sc": "太子道东, 采颐花园对面",
        "name_en": "Prince Edward Road East, opposite Rhythm Garden"
      },
      {
        "stop_seq": 11,
        "stop_id": 20014664,
        "name_tc": "太子道東, 譽.港灣對面",
        "name_sc": "太子道东, 誉.港湾对面",
        "name_en": "Prince Edward Road East, opposite The Latitude"
      },
      {
        "stop_seq": 12,
        "stop_id": 20012110,
        "name_tc": "太子道東, 富豪東方酒店對面",
        "name_sc": "太子道东, 富豪东方酒店对面",
        "name_en": "Prince Edward Road East, opposite Regal Oriental Hotel"
      },
      {
        "stop_seq": 13,
        "stop_id": 20014665,
        "name_tc": "馬頭涌道, 宋皇臺遊樂場外",
        "name_sc": "马头涌道, 宋皇台游乐场外",
        "name_en": "Ma Tau Chung Road, outside Sung Wong Toi Playground"
      },
      {
        "stop_seq": 14,
        "stop_id": 20014666,
        "name_tc": "馬頭涌道, 福安大廈外",
        "name_sc": "马头涌道, 福安大厦外",
        "name_en": "Ma Tau Chung Road, outside Fok On Building"
      },
      {
        "stop_seq": 15,
        "stop_id": 20014667,
        "name_tc": "馬頭涌道, 工聯會工人俱樂部大廈外",
        "name_sc": "马头涌道, 工联会工人俱乐部大厦外",
        "name_en": "Ma Tau Chung Road, outside The Hong Kong Federation Of Trade Unions Worker's Club"
      },
      {
        "stop_seq": 16,
        "stop_id": 20000440,
        "name_tc": "馬頭圍道187號",
        "name_sc": "马头围道187号",
        "name_en": "No.187 Ma Tau Wai Road"
      },
      {
        "stop_seq": 17,
        "stop_id": 20002012,
        "name_tc": "上鄉道37號",
        "name_sc": "上乡道37号",
        "name_en": "Sheung Heung Road, No.37"
      },
      {
        "stop_seq": 18,
        "stop_id": 20000490,
        "name_tc": "土瓜灣道, 土瓜灣大廈外",
        "name_sc": "土瓜湾道, 土瓜湾大厦外",
        "name_en": "To Kwa Wan Road, outside To Kwa Wan Mansion"
      },
      {
        "stop_seq": 19,
        "stop_id": 20002013,
        "name_tc": "土瓜灣道, 宏豐工業大廈外",
        "name_sc": "土瓜湾道, 宏丰工业大厦外",
        "name_en": "World Wide Industrial Building"
      },
      {
        "stop_seq": 20,
        "stop_id": 20014652,
        "name_tc": "高山道, 高山劇場外",
        "name_sc": "高山道, 高山剧场外",
        "name_en": "Ko Shan Road, outside Ko Shan Theatre"
      }
    ],
    "data_timestamp": "2024-08-07T13:52:30.575+08:00"
  }
}