{
  "type": "Route-Stop",
  "version": "1.0",
  "generated_timestamp": "2024-11-17T10:27:26.593+08:00",
  "data": {
    "route_stops": [
      {
        "stop_seq": 1,
        "stop_id": 20015726,
        "name_tc": "顯泰街, 近瑞峰花園",
        "name_sc": "显泰街, 近瑞峰花园",
        "name_en": "Hin Tai Street, near Julimount Garden"
      },
      {
        "stop_seq": 2,
        "stop_id": 20015731,
        "name_tc": "顯康街, 旭達商場外",
        "name_sc": "显康街, 旭达商场外",
        "name_en": "Hin Hong Street, outside Julimount Garden Shopping Centre"
      },
      {
        "stop_seq": 3,
        "stop_id": 20015725,
        "name_tc": "富健街, 仁安醫院外",
        "name_sc": "富健街, 仁安医院外",
        "name_en": "Fu Kin Street, outside Union Hospital"
      },
      {
        "stop_seq": 4,
        "stop_id": 20015732,
        "name_tc": "富健街, 隆亨邨善心樓對面",
        "name_sc": "富健街, 隆亨邨善心楼对面",
        "name_en": "Fu Kin Street, opposite Sin Sam House, Lung Hang Estate"
      },
      {
        "stop_seq": 5,
        "stop_id": 20015741,
        "name_tc": "車公廟路, 近顯徑站",
        "name_sc": "车公庙路, 近显径站",
        "name_en": "Che Kung Miu Road, near Hin Keng Station"
      }
    ],
    "data_timestamp": "2024-07-21T00:00:39.401+08:00"
  }
}