[
  {
    "方向": "中環 至 長洲",
    "服務日子": "星期一至六 (公眾假期除外)",
    "服務時段": "12:30 a.m.",
    "備註": ""
  },
  {
    "方向": "中環 至 長洲",
    "服務日子": "星期一至六 (公眾假期除外)",
    "服務時段": "1:30 a.m.",
    "備註": ""
  },
  {
    "方向": "中環 至 長洲",
    "服務日子": "星期一至六 (公眾假期除外)",
    "服務時段": "4:15 a.m.",
    "備註": ""
  },
  {
    "方向": "中環 至 長洲",
    "服務日子": "星期一至六 (公眾假期除外)",
    "服務時段": "6:10 a.m.",
    "備註": "1"
  },
  {
    "方向": "中環 至 長洲",
    "服務日子": "星期一至六 (公眾假期除外)",
    "服務時段": "7:00 a.m.",
    "備註": ""
  },
  {
    "方向": "中環 至 長洲",
    "服務日子": "星期一至六 (公眾假期除外)",
    "服務時段": "7:40 a.m.",
    "備註": "1"
  },
  {
    "方向": "中環 至 長洲",
    "服務日子": "星期一至六 (公眾假期除外)",
    "服務時段": "8:00 a.m.",
    "備註": ""
  },
  {
    "方向": "中環 至 長洲",
    "服務日子": "星期一至六 (公眾假期除外)",
    "服務時段": "8:40 a.m.",
    "備註": ""
  },
  {
    "方向": "中環 至 長洲",
    "服務日子": "星期一至六 (公眾假期除外)",
    "服務時段": "9:00 a.m.",
    "備註": "1"
  },
  {
    "方向": "中環 至 長洲",
    "服務日子": "星期一至六 (公眾假期除外)",
    "服務時段": "9:45 a.m.",
    "備註": ""
  },
  {
    "方向": "中環 至 長洲",
    "服務日子": "星期一至六 (公眾假期除外)",
    "服務時段": "10:15 a.m.",
    "備註": "1"
  },
  {
    "方向": "中環 至 長洲",
    "服務日子": "星期一至六 (公眾假期除外)",
    "服務時段": "10:45 a.m.",
    "備註": ""
  },
  {
    "方向": "中環 至 長洲",
    "服務日子": "星期一至六 (公眾假期除外)",
    "服務時段": "11:15 a.m.",
    "備註": "1"
  },
  {
    "方向": "中環 至 長洲",
    "服務日子": "星期一至六 (公眾假期除外)",
    "服務時段": "11:45 a.m.",
    "備註": ""
  },
  {
    "方向": "中環 至 長洲",
    "服務日子": "星期一至六 (公眾假期除外)",
    "服務時段": "12:15 p.m.",
    "備註": "1"
  },
  {
    "方向": "中環 至 長洲",
    "服務日子": "星期一至六 (公眾假期除外)",
    "服務時段": "12:45 p.m.",
    "備註": ""
  },
  {
    "方向": "中環 至 長洲",
    "服務日子": "星期一至六 (公眾假期除外)",
    "服務時段": "1:15 p.m.",
    "備註": "1"
  },
  {
    "方向": "中環 至 長洲",
    "服務日子": "星期一至六 (公眾假期除外)",
    "服務時段": "1:45 p.m.",
    "備註": ""
  },
  {
    "方向": "中環 至 長洲",
    "服務日子": "星期一至六 (公眾假期除外)",
    "服務時段": "2:15 p.m.",
    "備註": "1"
  },
  {
    "方向": "中環 至 長洲",
    "服務日子": "星期一至六 (公眾假期除外)",
    "服務時段": "2:45 p.m.",
    "備註": ""
  },
  {
    "方向": "中環 至 長洲",
    "服務日子": "星期一至六 (公眾假期除外)",
    "服務時段": "3:15 p.m.",
    "備註": "1"
  },
  {
    "方向": "中環 至 長洲",
    "服務日子": "星期一至六 (公眾假期除外)",
    "服務時段": "3:45 p.m.",
    "備註": ""
  },
  {
    "方向": "中環 至 長洲",
    "服務日子": "星期一至六 (公眾假期除外)",
    "服務時段": "4:15 p.m.",
    "備註": "1"
  },
  {
    "方向": "中環 至 長洲",
    "服務日子": "星期一至六 (公眾假期除外)",
    "服務時段": "4:45 p.m.",
    "備註": ""
  },
  {
    "方向": "中環 至 長洲",
    "服務日子": "星期一至六 (公眾假期除外)",
    "服務時段": "5:20 p.m.",
    "備註": "1"
  },
  {
    "方向": "中環 至 長洲",
    "服務日子": "星期一至六 (公眾假期除外)",
    "服務時段": "5:40 p.m.",
    "備註": ""
  },
  {
    "方向": "中環 至 長洲",
    "服務日子": "星期一至六 (公眾假期除外)",
    "服務時段": "6:00 p.m.",
    "備註": "1"
  },
  {
    "方向": "中環 至 長洲",
    "服務日子": "星期一至六 (公眾假期除外)",
    "服務時段": "6:20 p.m.",
    "備註": ""
  },
  {
    "方向": "中環 至 長洲",
    "服務日子": "星期一至六 (公眾假期除外)",
    "服務時段": "6:45 p.m.",
    "備註": "1"
  },
  {
    "方向": "中環 至 長洲",
    "服務日子": "星期一至六 (公眾假期除外)",
    "服務時段": "7:00 p.m.",
    "備註": ""
  },
  {
    "方向": "中環 至 長洲",
    "服務日子": "星期一至六 (公眾假期除外)",
    "服務時段": "7:15 p.m.",
    "備註": "2"
  },
  {
    "方向": "中環 至 長洲",
    "服務日子": "星期一至六 (公眾假期除外)",
    "服務時段": "7:30 p.m.",
    "備註": "3"
  },
  {
    "方向": "中環 至 長洲",
    "服務日子": "星期一至六 (公眾假期除外)",
    "服務時段": "7:40 p.m.",
    "備註": "4"
  },
  {
    "方向": "中環 至 長洲",
    "服務日子": "星期一至六 (公眾假期除外)",
    "服務時段": "8:00 p.m.",
    "備註": ""
  },
  {
    "方向": "中環 至 長洲",
    "服務日子": "星期一至六 (公眾假期除外)",
    "服務時段": "8:30 p.m.",
    "備註": "1"
  },
  {
    "方向": "中環 至 長洲",
    "服務日子": "星期一至六 (公眾假期除外)",
    "服務時段": "9:00 p.m.",
    "備註": ""
  },
  {
    "方向": "中環 至 長洲",
    "服務日子": "星期一至六 (公眾假期除外)",
    "服務時段": "9:30 p.m.",
    "備註": "1"
  },
  {
    "方向": "中環 至 長洲",
    "服務日子": "星期一至六 (公眾假期除外)",
    "服務時段": "10:00 p.m.",
    "備註": ""
  },
  {
    "方向": "中環 至 長洲",
    "服務日子": "星期一至六 (公眾假期除外)",
    "服務時段": "10:30 p.m.",
    "備註": "1"
  },
  {
    "方向": "中環 至 長洲",
    "服務日子": "星期一至六 (公眾假期除外)",
    "服務時段": "11:00 p.m.",
    "備註": ""
  },
  {
    "方向": "中環 至 長洲",
    "服務日子": "星期一至六 (公眾假期除外)",
    "服務時段": "11:30 p.m.",
    "備註": "1"
  },
  {
    "方向": "中環 至 長洲",
    "服務日子": "星期一至六 (公眾假期除外)",
    "服務時段": "11:45 p.m.",
    "備註": ""
  },
  {
    "方向": "長洲 至 中環",
    "服務日子": "星期一至六 (公眾假期除外)",
    "服務時段": "2:20 a.m.",
    "備註": ""
  },
  {
    "方向": "長洲 至 中環",
    "服務日子": "星期一至六 (公眾假期除外)",
    "服務時段": "5:10 a.m.",
    "備註": ""
  },
  {
    "方向": "長洲 至 中環",
    "服務日子": "星期一至六 (公眾假期除外)",
    "服務時段": "5:50 a.m.",
    "備註": "1"
  },
  {
    "方向": "長洲 至 中環",
    "服務日子": "星期一至六 (公眾假期除外)",
    "服務時段": "6:20 a.m.",
    "備註": ""
  },
  {
    "方向": "長洲 至 中環",
    "服務日子": "星期一至六 (公眾假期除外)",
    "服務時段": "6:40 a.m.",
    "備註": "1"
  },
  {
    "方向": "長洲 至 中環",
    "服務日子": "星期一至六 (公眾假期除外)",
    "服務時段": "7:00 a.m.",
    "備註": ""
  },
  {
    "方向": "長洲 至 中環",
    "服務日子": "星期一至六 (公眾假期除外)",
    "服務時段": "7:15 a.m.",
    "備註": "1"
  },
  {
    "方向": "長洲 至 中環",
    "服務日子": "星期一至六 (公眾假期除外)",
    "服務時段": "7:45 a.m.",
    "備註": ""
  },
  {
    "方向": "長洲 至 中環",
    "服務日子": "星期一至六 (公眾假期除外)",
    "服務時段": "7:50 a.m.",
    "備註": "1"
  },
  {
    "方向": "長洲 至 中環",
    "服務日子": "星期一至六 (公眾假期除外)",
    "服務時段": "7:55 a.m.",
    "備註": ""
  },
  {
    "方向": "長洲 至 中環",
    "服務日子": "星期一至六 (公眾假期除外)",
    "服務時段": "8:10 a.m.",
    "備註": ""
  },
  {
    "方向": "長洲 至 中環",
    "服務日子": "星期一至六 (公眾假期除外)",
    "服務時段": "8:20 a.m.",
    "備註": ""
  },
  {
    "方向": "長洲 至 中環",
    "服務日子": "星期一至六 (公眾假期除外)",
    "服務時段": "8:40 a.m.",
    "備註": "1"
  },
  {
    "方向": "長洲 至 中環",
    "服務日子": "星期一至六 (公眾假期除外)",
    "服務時段": "9:00 a.m.",
    "備註": ""
  },
  {
    "方向": "長洲 至 中環",
    "服務日子": "星期一至六 (公眾假期除外)",
    "服務時段": "9:30 a.m.",
    "備註": ""
  },
  {
    "方向": "長洲 至 中環",
    "服務日子": "星期一至六 (公眾假期除外)",
    "服務時段": "10:00 a.m.",
    "備註": "1"
  },
  {
    "方向": "長洲 至 中環",
    "服務日子": "星期一至六 (公眾假期除外)",
    "服務時段": "10:45 a.m.",
    "備註": ""
  },
  {
    "方向": "長洲 至 中環",
    "服務日子": "星期一至六 (公眾假期除外)",
    "服務時段": "11:15 a.m.",
    "備註": "1"
  },
  {
    "方向": "長洲 至 中環",
    "服務日子": "星期一至六 (公眾假期除外)",
    "服務時段": "11:45 a.m.",
    "備註": ""
  },
  {
    "方向": "長洲 至 中環",
    "服務日子": "星期一至六 (公眾假期除外)",
    "服務時段": "12:15 p.m.",
    "備註": "1"
  },
  {
    "方向": "長洲 至 中環",
    "服務日子": "星期一至六 (公眾假期除外)",
    "服務時段": "12:45 p.m.",
    "備註": ""
  },
  {
    "方向": "長洲 至 中環",
    "服務日子": "星期一至六 (公眾假期除外)",
    "服務時段": "1:15 p.m.",
    "備註": "1"
  },
  {
    "方向": "長洲 至 中環",
    "服務日子": "星期一至六 (公眾假期除外)",
    "服務時段": "1:45 p.m.",
    "備註": ""
  },
  {
    "方向": "長洲 至 中環",
    "服務日子": "星期一至六 (公眾假期除外)",
    "服務時段": "2:15 p.m.",
    "備註": "1"
  },
  {
    "方向": "長洲 至 中環",
    "服務日子": "星期一至六 (公眾假期除外)",
    "服務時段": "2:45 p.m.",
    "備註": ""
  },
  {
    "方向": "長洲 至 中環",
    "服務日子": "星期一至六 (公眾假期除外)",
    "服務時段": "3:15 p.m.",
    "備註": "1"
  },
  {
    "方向": "長洲 至 中環",
    "服務日子": "星期一至六 (公眾假期除外)",
    "服務時段": "3:45 p.m.",
    "備註": ""
  },
  {
    "方向": "長洲 至 中環",
    "服務日子": "星期一至六 (公眾假期除外)",
    "服務時段": "4:15 p.m.",
    "備註": "1"
  },
  {
    "方向": "長洲 至 中環",
    "服務日子": "星期一至六 (公眾假期除外)",
    "服務時段": "4:45 p.m.",
    "備註": ""
  },
  {
    "方向": "長洲 至 中環",
    "服務日子": "星期一至六 (公眾假期除外)",
    "服務時段": "5:15 p.m.",
    "備註": "1"
  },
  {
    "方向": "長洲 至 中環",
    "服務日子": "星期一至六 (公眾假期除外)",
    "服務時段": "5:40 p.m.",
    "備註": ""
  },
  {
    "方向": "長洲 至 中環",
    "服務日子": "星期一至六 (公眾假期除外)",
    "服務時段": "6:20 p.m.",
    "備註": "1"
  },
  {
    "方向": "長洲 至 中環",
    "服務日子": "星期一至六 (公眾假期除外)",
    "服務時段": "7:00 p.m.",
    "備註": ""
  },
  {
    "方向": "長洲 至 中環",
    "服務日子": "星期一至六 (公眾假期除外)",
    "服務時段": "7:30 p.m.",
    "備註": "1"
  },
  {
    "方向": "長洲 至 中環",
    "服務日子": "星期一至六 (公眾假期除外)",
    "服務時段": "8:00 p.m.",
    "備註": ""
  },
  {
    "方向": "長洲 至 中環",
    "服務日子": "星期一至六 (公眾假期除外)",
    "服務時段": "8:30 p.m.",
    "備註": "1"
  },
  {
    "方向": "長洲 至 中環",
    "服務日子": "星期一至六 (公眾假期除外)",
    "服務時段": "9:00 p.m.",
    "備註": ""
  },
  {
    "方向": "長洲 至 中環",
    "服務日子": "星期一至六 (公眾假期除外)",
    "服務時段": "9:30 p.m.",
    "備註": "1"
  },
  {
    "方向": "長洲 至 中環",
    "服務日子": "星期一至六 (公眾假期除外)",
    "服務時段": "10:00 p.m.",
    "備註": ""
  },
  {
    "方向": "長洲 至 中環",
    "服務日子": "星期一至六 (公眾假期除外)",
    "服務時段": "10:30 p.m.",
    "備註": "1"
  },
  {
    "方向": "長洲 至 中環",
    "服務日子": "星期一至六 (公眾假期除外)",
    "服務時段": "11:00 p.m.",
    "備註": ""
  },
  {
    "方向": "長洲 至 中環",
    "服務日子": "星期一至六 (公眾假期除外)",
    "服務時段": "11:30 p.m.",
    "備註": "1"
  },
  {
    "方向": "長洲 至 中環",
    "服務日子": "星期一至六 (公眾假期除外)",
    "服務時段": "11:45 p.m.",
    "備註": ""
  },
  {
    "方向": "中環 至 長洲",
    "服務日子": "星期日及公眾假期",
    "服務時段": "12:30 a.m.",
    "備註": ""
  },
  {
    "方向": "中環 至 長洲",
    "服務日子": "星期日及公眾假期",
    "服務時段": "1:30 a.m.",
    "備註": ""
  },
  {
    "方向": "中環 至 長洲",
    "服務日子": "星期日及公眾假期",
    "服務時段": "4:15 a.m.",
    "備註": ""
  },
  {
    "方向": "中環 至 長洲",
    "服務日子": "星期日及公眾假期",
    "服務時段": "6:30 a.m.",
    "備註": "1"
  },
  {
    "方向": "中環 至 長洲",
    "服務日子": "星期日及公眾假期",
    "服務時段": "7:00 a.m.",
    "備註": ""
  },
  {
    "方向": "中環 至 長洲",
    "服務日子": "星期日及公眾假期",
    "服務時段": "7:30 a.m.",
    "備註": "1"
  },
  {
    "方向": "中環 至 長洲",
    "服務日子": "星期日及公眾假期",
    "服務時段": "8:00 a.m.",
    "備註": ""
  },
  {
    "方向": "中環 至 長洲",
    "服務日子": "星期日及公眾假期",
    "服務時段": "8:30 a.m.",
    "備註": "1"
  },
  {
    "方向": "中環 至 長洲",
    "服務日子": "星期日及公眾假期",
    "服務時段": "9:00 a.m.",
    "備註": ""
  },
  {
    "方向": "中環 至 長洲",
    "服務日子": "星期日及公眾假期",
    "服務時段": "9:30 a.m.",
    "備註": "1"
  },
  {
    "方向": "中環 至 長洲",
    "服務日子": "星期日及公眾假期",
    "服務時段": "10:00 a.m.",
    "備註": ""
  },
  {
    "方向": "中環 至 長洲",
    "服務日子": "星期日及公眾假期",
    "服務時段": "10:30 a.m.",
    "備註": "1"
  },
  {
    "方向": "中環 至 長洲",
    "服務日子": "星期日及公眾假期",
    "服務時段": "11:00 a.m.",
    "備註": ""
  },
  {
    "方向": "中環 至 長洲",
    "服務日子": "星期日及公眾假期",
    "服務時段": "11:30 a.m.",
    "備註": "1"
  },
  {
    "方向": "中環 至 長洲",
    "服務日子": "星期日及公眾假期",
    "服務時段": "12:00 p.m.",
    "備註": ""
  },
  {
    "方向": "中環 至 長洲",
    "服務日子": "星期日及公眾假期",
    "服務時段": "12:30 p.m.",
    "備註": "1"
  },
  {
    "方向": "中環 至 長洲",
    "服務日子": "星期日及公眾假期",
    "服務時段": "1:00 p.m.",
    "備註": ""
  },
  {
    "方向": "中環 至 長洲",
    "服務日子": "星期日及公眾假期",
    "服務時段": "1:30 p.m.",
    "備註": "1"
  },
  {
    "方向": "中環 至 長洲",
    "服務日子": "星期日及公眾假期",
    "服務時段": "2:00 p.m.",
    "備註": ""
  },
  {
    "方向": "中環 至 長洲",
    "服務日子": "星期日及公眾假期",
    "服務時段": "2:30 p.m.",
    "備註": "1"
  },
  {
    "方向": "中環 至 長洲",
    "服務日子": "星期日及公眾假期",
    "服務時段": "3:00 p.m.",
    "備註": ""
  },
  {
    "方向": "中環 至 長洲",
    "服務日子": "星期日及公眾假期",
    "服務時段": "3:30 p.m.",
    "備註": "1"
  },
  {
    "方向": "中環 至 長洲",
    "服務日子": "星期日及公眾假期",
    "服務時段": "4:00 p.m.",
    "備註": ""
  },
  {
    "方向": "中環 至 長洲",
    "服務日子": "星期日及公眾假期",
    "服務時段": "4:30 p.m.",
    "備註": "1"
  },
  {
    "方向": "中環 至 長洲",
    "服務日子": "星期日及公眾假期",
    "服務時段": "5:00 p.m.",
    "備註": ""
  },
  {
    "方向": "中環 至 長洲",
    "服務日子": "星期日及公眾假期",
    "服務時段": "5:30 p.m.",
    "備註": "1"
  },
  {
    "方向": "中環 至 長洲",
    "服務日子": "星期日及公眾假期",
    "服務時段": "6:00 p.m.",
    "備註": ""
  },
  {
    "方向": "中環 至 長洲",
    "服務日子": "星期日及公眾假期",
    "服務時段": "6:30 p.m.",
    "備註": "1"
  },
  {
    "方向": "中環 至 長洲",
    "服務日子": "星期日及公眾假期",
    "服務時段": "7:00 p.m.",
    "備註": ""
  },
  {
    "方向": "中環 至 長洲",
    "服務日子": "星期日及公眾假期",
    "服務時段": "7:30 p.m.",
    "備註": "1"
  },
  {
    "方向": "中環 至 長洲",
    "服務日子": "星期日及公眾假期",
    "服務時段": "8:00 p.m.",
    "備註": ""
  },
  {
    "方向": "中環 至 長洲",
    "服務日子": "星期日及公眾假期",
    "服務時段": "8:30 p.m.",
    "備註": "1"
  },
  {
    "方向": "中環 至 長洲",
    "服務日子": "星期日及公眾假期",
    "服務時段": "9:00 p.m.",
    "備註": ""
  },
  {
    "方向": "中環 至 長洲",
    "服務日子": "星期日及公眾假期",
    "服務時段": "9:30 p.m.",
    "備註": "1"
  },
  {
    "方向": "中環 至 長洲",
    "服務日子": "星期日及公眾假期",
    "服務時段": "10:00 p.m.",
    "備註": ""
  },
  {
    "方向": "中環 至 長洲",
    "服務日子": "星期日及公眾假期",
    "服務時段": "10:30 p.m.",
    "備註": "1"
  },
  {
    "方向": "中環 至 長洲",
    "服務日子": "星期日及公眾假期",
    "服務時段": "11:00 p.m.",
    "備註": ""
  },
  {
    "方向": "中環 至 長洲",
    "服務日子": "星期日及公眾假期",
    "服務時段": "11:30 p.m.",
    "備註": "1"
  },
  {
    "方向": "中環 至 長洲",
    "服務日子": "星期日及公眾假期",
    "服務時段": "11:55 p.m.",
    "備註": ""
  },
  {
    "方向": "長洲 至 中環",
    "服務日子": "星期日及公眾假期",
    "服務時段": "2:20 a.m.",
    "備註": ""
  },
  {
    "方向": "長洲 至 中環",
    "服務日子": "星期日及公眾假期",
    "服務時段": "5:10 a.m.",
    "備註": ""
  },
  {
    "方向": "長洲 至 中環",
    "服務日子": "星期日及公眾假期",
    "服務時段": "6:00 a.m.",
    "備註": ""
  },
  {
    "方向": "長洲 至 中環",
    "服務日子": "星期日及公眾假期",
    "服務時段": "6:30 a.m.",
    "備註": "1"
  },
  {
    "方向": "長洲 至 中環",
    "服務日子": "星期日及公眾假期",
    "服務時段": "7:00 a.m.",
    "備註": ""
  },
  {
    "方向": "長洲 至 中環",
    "服務日子": "星期日及公眾假期",
    "服務時段": "7:30 a.m.",
    "備註": "1"
  },
  {
    "方向": "長洲 至 中環",
    "服務日子": "星期日及公眾假期",
    "服務時段": "8:00 a.m.",
    "備註": ""
  },
  {
    "方向": "長洲 至 中環",
    "服務日子": "星期日及公眾假期",
    "服務時段": "8:30 a.m.",
    "備註": "1"
  },
  {
    "方向": "長洲 至 中環",
    "服務日子": "星期日及公眾假期",
    "服務時段": "9:00 a.m.",
    "備註": ""
  },
  {
    "方向": "長洲 至 中環",
    "服務日子": "星期日及公眾假期",
    "服務時段": "9:30 a.m.",
    "備註": "1"
  },
  {
    "方向": "長洲 至 中環",
    "服務日子": "星期日及公眾假期",
    "服務時段": "10:00 a.m.",
    "備註": ""
  },
  {
    "方向": "長洲 至 中環",
    "服務日子": "星期日及公眾假期",
    "服務時段": "10:30 a.m.",
    "備註": "1"
  },
  {
    "方向": "長洲 至 中環",
    "服務日子": "星期日及公眾假期",
    "服務時段": "11:00 a.m.",
    "備註": ""
  },
  {
    "方向": "長洲 至 中環",
    "服務日子": "星期日及公眾假期",
    "服務時段": "11:30 a.m.",
    "備註": "1"
  },
  {
    "方向": "長洲 至 中環",
    "服務日子": "星期日及公眾假期",
    "服務時段": "12:00 p.m.",
    "備註": ""
  },
  {
    "方向": "長洲 至 中環",
    "服務日子": "星期日及公眾假期",
    "服務時段": "12:30 p.m.",
    "備註": "1"
  },
  {
    "方向": "長洲 至 中環",
    "服務日子": "星期日及公眾假期",
    "服務時段": "1:00 p.m.",
    "備註": ""
  },
  {
    "方向": "長洲 至 中環",
    "服務日子": "星期日及公眾假期",
    "服務時段": "1:30 p.m.",
    "備註": "1"
  },
  {
    "方向": "長洲 至 中環",
    "服務日子": "星期日及公眾假期",
    "服務時段": "2:00 p.m.",
    "備註": ""
  },
  {
    "方向": "長洲 至 中環",
    "服務日子": "星期日及公眾假期",
    "服務時段": "2:30 p.m.",
    "備註": "1"
  },
  {
    "方向": "長洲 至 中環",
    "服務日子": "星期日及公眾假期",
    "服務時段": "3:00 p.m.",
    "備註": ""
  },
  {
    "方向": "長洲 至 中環",
    "服務日子": "星期日及公眾假期",
    "服務時段": "3:30 p.m.",
    "備註": "1"
  },
  {
    "方向": "長洲 至 中環",
    "服務日子": "星期日及公眾假期",
    "服務時段": "4:00 p.m.",
    "備註": ""
  },
  {
    "方向": "長洲 至 中環",
    "服務日子": "星期日及公眾假期",
    "服務時段": "4:30 p.m.",
    "備註": "1"
  },
  {
    "方向": "長洲 至 中環",
    "服務日子": "星期日及公眾假期",
    "服務時段": "5:00 p.m.",
    "備註": ""
  },
  {
    "方向": "長洲 至 中環",
    "服務日子": "星期日及公眾假期",
    "服務時段": "5:30 p.m.",
    "備註": "1"
  },
  {
    "方向": "長洲 至 中環",
    "服務日子": "星期日及公眾假期",
    "服務時段": "6:00 p.m.",
    "備註": ""
  },
  {
    "方向": "長洲 至 中環",
    "服務日子": "星期日及公眾假期",
    "服務時段": "6:30 p.m.",
    "備註": "1"
  },
  {
    "方向": "長洲 至 中環",
    "服務日子": "星期日及公眾假期",
    "服務時段": "7:00 p.m.",
    "備註": ""
  },
  {
    "方向": "長洲 至 中環",
    "服務日子": "星期日及公眾假期",
    "服務時段": "7:30 p.m.",
    "備註": "1"
  },
  {
    "方向": "長洲 至 中環",
    "服務日子": "星期日及公眾假期",
    "服務時段": "8:00 p.m.",
    "備註": ""
  },
  {
    "方向": "長洲 至 中環",
    "服務日子": "星期日及公眾假期",
    "服務時段": "8:30 p.m.",
    "備註": "1"
  },
  {
    "方向": "長洲 至 中環",
    "服務日子": "星期日及公眾假期",
    "服務時段": "9:00 p.m.",
    "備註": ""
  },
  {
    "方向": "長洲 至 中環",
    "服務日子": "星期日及公眾假期",
    "服務時段": "9:30 p.m.",
    "備註": "1"
  },
  {
    "方向": "長洲 至 中環",
    "服務日子": "星期日及公眾假期",
    "服務時段": "10:00 p.m.",
    "備註": ""
  },
  {
    "方向": "長洲 至 中環",
    "服務日子": "星期日及公眾假期",
    "服務時段": "10:30 p.m.",
    "備註": "1"
  },
  {
    "方向": "長洲 至 中環",
    "服務日子": "星期日及公眾假期",
    "服務時段": "11:00 p.m.",
    "備註": ""
  },
  {
    "方向": "長洲 至 中環",
    "服務日子": "星期日及公眾假期",
    "服務時段": "11:30 p.m.",
    "備註": "1"
  }
]