{
  "type": "Route",
  "version": "1.0",
  "generated_timestamp": "2024-09-20T12:29:09.564+08:00",
  "data": [
    {
      "route_id": 2003207,
      "region": "NT",
      "route_code": "482",
      "description_tc": "正常班次",
      "description_sc": "正常班次",
      "description_en": "Normal Route",
      "directions": [
        {
          "route_seq": 1,
          "orig_tc": "沙⽥市中⼼(担杆莆街)",
          "orig_sc": "沙⽥市中⼼(担杆莆街)",
          "orig_en": "Sha Tin Central (Tam Kon Po Street)",
          "dest_tc": "荃灣街市街",
          "dest_sc": "荃湾街市街",
          "dest_en": "Tsuen Wan Market Street",
          "remarks_tc": null,
          "remarks_sc": null,
          "remarks_en": null,
          "headways": [
            {
              "weekdays": [
                true,
                true,
                true,
                true,
                true,
                true,
                true
              ],
              "public_holiday": true,
              "headway_seq": 1,
              "start_time": "23:30:00",
              "end_time": "06:00:00",
              "frequency": 30,
              "frequency_upper": null
            }
          ],
          "data_timestamp": "2024-07-31T16:58:38.764+08:00"
        },
        {
          "route_seq": 2,
          "orig_tc": "荃灣街市街",
          "orig_sc": "荃湾街市街",
          "orig_en": "Tsuen Wan Market Street",
          "dest_tc": "沙⽥市中⼼(担杆莆街)",
          "dest_sc": "沙⽥市中⼼(担杆莆街)",
          "dest_en": "Sha Tin Central (Tam Kon Po Street)",
          "remarks_tc": null,
          "remarks_sc": null,
          "remarks_en": null,
          "headways": [
            {
              "weekdays": [
                true,
                true,
                true,
                true,
                true,
                true,
                true
              ],
              "public_holiday": true,
              "headway_seq": 1,
              "start_time": "23:30:00",
              "end_time": "06:00:00",
              "frequency": 30,
              "frequency_upper": null
            }
          ],
          "data_timestamp": "2024-07-31T16:58:38.764+08:00"
        }
      ],
      "data_timestamp": "2024-07-31T16:58:38.764+08:00"
    }
  ]
}