{
  "type": "Route",
  "version": "1.0",
  "generated_timestamp": "2024-09-20T12:28:48.644+08:00",
  "data": [
    {
      "route_id": 2003306,
      "region": "NT",
      "route_code": "402S",
      "description_tc": "通宵班次",
      "description_sc": "通宵班次",
      "description_en": "Midnight Service",
      "directions": [
        {
          "route_seq": 1,
          "orig_tc": "長亨",
          "orig_sc": "长亨",
          "orig_en": "Cheung Hang",
          "dest_tc": "荃灣(眾安街)",
          "dest_sc": "荃湾(众安街)",
          "dest_en": "Tsuen Wan (Chung On Street)",
          "remarks_tc": null,
          "remarks_sc": null,
          "remarks_en": null,
          "headways": [
            {
              "weekdays": [
                true,
                true,
                true,
                true,
                true,
                true,
                true
              ],
              "public_holiday": true,
              "headway_seq": 1,
              "start_time": "23:50:00",
              "end_time": "05:25:00",
              "frequency": 25,
              "frequency_upper": null
            }
          ],
          "data_timestamp": "2024-09-08T00:00:32.115+08:00"
        },
        {
          "route_seq": 2,
          "orig_tc": "荃灣(眾安街)",
          "orig_sc": "荃湾(众安街)",
          "orig_en": "Tsuen Wan (Chung On Street)",
          "dest_tc": "長亨",
          "dest_sc": "长亨",
          "dest_en": "Cheung Hang",
          "remarks_tc": null,
          "remarks_sc": null,
          "remarks_en": null,
          "headways": [
            {
              "weekdays": [
                true,
                true,
                true,
                true,
                true,
                true,
                true
              ],
              "public_holiday": true,
              "headway_seq": 1,
              "start_time": "23:50:00",
              "end_time": "05:25:00",
              "frequency": 25,
              "frequency_upper": null
            }
          ],
          "data_timestamp": "2024-09-08T00:00:32.115+08:00"
        }
      ],
      "data_timestamp": "2024-09-08T00:00:32.115+08:00"
    }
  ]
}